{
  "summary": {
    "半花瓣指环虫：（DactylogyrushemipetaloideusZhangetGuo,1986）是指环虫属昆虫": {}
  },
  "main_body": {
    "形态特征": {
      "成虫：形态据张剑英、郭起治描述，虫体小型，体长0.195-0.507mm，宽0.044----0.057mm": {},
      "后吸器：与体分界明显，具2联结片，大小0.044----0.086×0.057—": {},
      "0.083：mm": {},
      "边缘：小钩全长0.018-0.039mm": {},
      "中央大钩：呈D.petaloideusZhangetji型，内、外突分化不明显，全长0.026---0.031mm，钩尖长0.009--0.OlOmm": {},
      "联结：片两端向后稍弯，中部向后突，大小0.003×0.018-0.023mm": {},
      "副联结片：细长，呈W状，大小0.001--0.002×0.018---0.026mm": {},
      "交接器：全长0.014-0.018mm": {},
      "交接管：基部扩大，管长0.012-0.019mm，基径0.001-0.003mm": {},
      "支持器：长0.014-0.018mm，是由两片花瓣状的几丁质片构成，并形成一弧形槽，交接管从槽中穿行": {},
      "卵：与阴道未见": {}
    },
    "生活习性": {
      "宿主：拟粲": {},
      "寄生部位：鳃": {}
    },
    "分布范围": {
      "分布：云南(剥隘)": {}
    },
    "参考文献": {}
  },
  "table": {}
}