{"summary": {"四川长柄茧蜂：，Streblocerasichuanensis（Wang，1986），属于茧蜂科长柄茧蜂属的一种昆虫": {}}, "main_body": {"形态特征": {"雌：体长约2.7mm，前翅长3.1mm": {}, "体：黑色": {}, "触角：基部第l、2节及第3节基部之半褐色，其余各节褐黑色": {}, "须：黄色": {}, "颜面：(除两触角之间的下方褐黑色)、唇基、上颚、颊、单眼、后颊、足(除后足跗节黑褐色及端跗节褐黑色)褐色": {}, "产卵管鞘：褐黑色": {}, "翅：透明，基脉与翅痣灰黄色，其余翅脉灰至灰黑色": {}, "头：背面观横宽，侧面观大致呈三角形": {}, "颜面：的中部略隆起，密生细小刻点及细毛，在两触角下方具有轻微皱褶": {}, "颚眼：距短，仅约上颚基部宽的3/4": {}, "触角：21节，第1节(即柄节)细长，不具齿状突起，其长略短于其后4节长度之和，在第1节与第2节之间屈折，但干标本不见屈折": {}, "胸前：胸背板能反光，横脊微弱，侧区凹，无明显横脊": {}, "中胸：背板光滑能反光，盾纵沟细，后方相遇处呈v字形，v字尖端与中胸背板后缘离开，在V形尖端处有皱褶": {}, "中胸：侧板光滑并能反光，侧板沟具细皱褶，其前端短，不能达侧板前缘，侧板沟的中部宽，侧板沟的后端部分较窄，伸达中足基节基部附近": {}, "中胸：侧板在侧板沟的上面部分中问略偏后处有一条与侧板沟近似垂直的弯的凹陷": {}, "并胸腹节：基脊与基横脊均甚明显，基脊两侧的背区光滑能反光，该节的侧区及该节的后半部表面粗绉，具不规则隆脊且能反光，中纵脊与侧纵脊亦较明显": {}, "胸部：生有白色短柔毛": {}, "腹短于头胸之和，：整个腹部光滑，有光泽": {}, "第：l背板端宽约为其长的2/5，气门位于该背板中央之前，两气门之间距为气门至该背板端部的2/5，该背板在气门之前的两侧有脊，中部内凹，在气门之后的两侧有少许细纵脊": {}, "产卵管：显露，末端弯": {}, "腹部：有极少白色短柔毛": {}}, "分布范围": {"分布：四川（乡城）。": {}}, "资料来源": {}}, "table": {}}