{"summary": {"将乐华溪蟹：，学名：Sinopotamonjianglense(Dai,1993)，为溪蟹科华溪蟹属的一种动物": {}, "常：生活于淡水，生活于溪流石块下，溪水清沏透明、四周植被茂密": {}, "其：生存的海拔范围为300至700米": {}}, "main_body": {"形态特征": {"观察标本": {"标本：8♂♂(7幼)12♀♀(10幼)，福建将乐将军顶里山，1991，8，16": {}, "标本：2♂♂1♀，福建将乐龙栖山，1991，8，21": {}, "标本：4♂♂(4幼)7♀♀(1抱卵)，福建将乐余家坪，1991，8，5": {}, "标本：1♂，福建将乐龙栖山沙溪子，1991，8，6": {}, "标本：8♂♂1♀(幼)，福建将乐石排厂，1991，8，7": {}, "标本：8♂♂(4幼)6♀♀(5幼)，福建将乐龙井，1991，8，5": {}, "标本：8♂♂(7幼)12♀♀(1抱卵)，福建将乐龙栖山村头，1991，8，12": {}, "标本：1♂，福建永安，1989，9": {}, "标本：5♂♂(5幼)10♀♀(9幼)，福建三明将乐，1981，5": {}, "标本：3♂♂2♀♀(1幼)，福建华安，1977，4—5": {}, "标本：4♂♂(3幼)8♀♀(8幼)，福建漳平，1978，6": {}, "标本：11♂♂(4幼)2♀♀(2幼)，广东梅县，1987，3，18": {}}, "形态描述": {"个体：中大型，头胸甲平坦，表面具麻凹点，前鳃区具细皱襞": {}, "颈：沟较宽而明显，胃、心区之间的H形沟细而深": {}, "额：后叶突起，眼后隆脊平钝，眼后区稍凹": {}, "额缘：中部内凹，背眼缘埂起，外眼窝角三角形，其外缘约具颗粒齿7枚": {}, "前鳃：齿不甚突出，前侧缘隆脊形，具颗粒齿12—14枚": {}, "第三颚足：长节的宽度约当长度的1．2倍，坐节的长度约当宽度的1．7倍，外肢粗壮，约抵长节基部的1／3，具鞭": {}}, "两螯：不对称，腕节背面中部具一纵沟，内末角具一壮刺，其基部具一小刺": {}, "大螯：掌部长度约当高度的1．5倍，约当可动指长的1．1倍，两指内缘具大小不等圆钝的三角形齿，合并时几无空隙": {}, "步足：粗壮，末对步足前节的长度约当宽度的1．5倍，约与指节等长": {}, "雄性：腹部呈窄长的三角形，第六节基部的宽度约当长度的1．6倍，尾节呈圆钝的舌形，基部宽度约当长度的1．1倍": {}, "胸部：腹甲沟略深，胸甲缝的间隔沟略窄，第七八节的中纵缝中等长度": {}, "第一腹肢：末端不甚抵达5—6节胸甲缝，末第二节约当末节长的4．6倍，末节向末部趋窄，末端弯向腹外侧": {}, "第二腹肢：末第二节约当末节长的3．2倍": {}, "雌性：腹部宽卵圆形，第六节的宽度约当长度的2．8倍，尾节基部宽度约当长度的2．1倍": {}, "生殖孔：呈卵圆形": {}, "雄性：头胸甲长27．2mm，宽34．9mm": {}, "雌性：长26．6mm，宽32．1mm": {}}, "生活习性": {"生活：于海拔300—700m处溪流石块下，水深约0．5—1m，溪水清澈透明，pH值6．5，夏季水温24—25℃，四周植被茂密": {}, "7：—8月份为其繁殖季节，母体抱卵约80余粒，卵粒直径约2．5mm": {}, "卵粒：发育很不一致": {}, "外层：的卵多先孵化，内层的卵仍在胚胎期": {}}, "分布范围": {"分布：在中国大陆，分布于福建、广东等地。": {}}}, "table": {}}