{"summary": {"少圈毛斑蚜：（AntisymydobiuspaucisensoriusZhang，ZhangetZhong,1993）是斑蚜科，毛斑蚜属的一种动物": {}, "分布：于中国吉林，寄主为桦木属": {}, "形态：为无翅孤雌蚜体椭圆形，玻片标本头前部、中胸黑色，腹部淡色，后胸及腹部背片Ⅰ-Ⅶ各有独立缘斑": {}}, "main_body": {"形态特征": {"无翅孤雌蚜体：椭圆形，玻片标本头前部、中胸黑色，腹部淡色，后胸及腹部背片Ⅰ-Ⅶ各有独立缘斑，各节有中侧断续黑斑，呈横带，背片Ⅷ横贯全节": {}, "触角Ⅰ、Ⅱ及Ⅳ-Ⅵ各：端部黑色，喙黑色，足全褐色，后足各节及前、中足股节端部、胫节两端及跗节黑色，腹管、尾片、尾板及生殖板黑色": {}, "体表：粗糙，由小粗刻点组成横瓦纹，腹面由小刺突组成瓦纹": {}, "气门：圆形关闭，气门片黑色": {}, "节间：斑明显黑褐色": {}, "缘瘤：小圆形，透明": {}, "中：胸腹岔褐色无柄": {}, "体背毛：多尖锐": {}, "头顶：不隆，呈平顶状": {}, "触角：有瓦纹，节Ⅲ有小圆形次生感觉圈": {}, "喙：粗大，不达后足基节，节Ⅳ+Ⅴ楔状": {}, "足：有稀的小刺突分布": {}, "腹管：圆筒状，有粗刺突横纹，无缘突和切迹，端径收缩": {}, "尾片：帽状，有粗刻纹组成横纹，有长尖锐毛": {}, "尾板：末端平圆形": {}}, "分布范围": {"分布：中国特有，分布于吉林。": {}}}, "table": {}}