{"summary": {"尼纳蠼螋：(NalanepalensisBurr,1907)是蠼螋科纳蠼螋属的一种动物": {}}, "main_body": {"形态特征": {"体型：狭小，微有光泽，污黑色，触角褐色或褐黄色，足的腿节和胫节的后半部为浅黄色": {}, "头部：圆隆，头缝不明显": {}, "复眼：小，稍小于眼后距的1／2": {}, "触角：细长，21节，基节长大，第2节长宽几相等，第3节长于第2节的2倍，第4节为第3节的l／2，第5节和第6节均和第4节等长，其余各节逐节稍增长": {}, "前胸：背板宽窄于长，后部稍宽，两侧近于平行，后缘圆弧形": {}, "背面：中缝稍显": {}, "鞘翅：长，具全长侧隆脊，后缘截形，背面密布小刻点": {}, "翅：柄短小，外缘弧形": {}, "腹部：两侧向后稍膨扩，遍布黄色短绒毛，末腹背板稍短宽，近于矩形，背面中沟明显": {}, "亚末腹：板后缘较钝": {}, "尾铗：基部2／5内缘扁扩，锯齿状，后内角较尖，后3／5近于弧形，末端尖向内侧弯曲，雄性外生殖器的阳茎基侧突较长": {}, "雌虫：与雄虫近似，末腹背板前宽后窄，亚末腹板末端较尖": {}, "尾铗：较短，基部内缘不扩展，末端尖": {}, "体长：9．25-13mm(包括尾铗)，7．5-11mm(不包括尾铗)。": {}}, "分布范围": {"国内分布": {"分布：湖南省": {}, "分布：福建省-三明市": {}, "分布：福建省-三明市-将乐县-龙栖山": {}, "分布：云南省": {}, "分布：福建省-三明市-将乐县": {}, "分布：福建省": {}}, "国外分布": {"分布：尼泊尔，印度，马来西亚，阿富汗": {}}}}, "table": {}}