{"summary": {"德门米虾：（CaridinademenicaCaietLi,1997）是匙指虾科，米虾属的一种动物": {}, "额角：极短，上、下缘均无齿，仅伸至第1触角柄基节的中部，头胸甲的触角钝圆，没有触角刺，前侧角圆，无颊刺": {}, "生活：于永康村德门洞中": {}, "分布：于贵州省-黔南布依族苗族自治州-荔波县": {}}, "main_body": {"形态特征": {"额角：极短，上、下缘均无齿，仅伸至第1触角柄基节的中部，头胸甲的触角钝圆，没有触角刺，前侧角圆，无颊刺": {}, "眼：退化，但仍留色素点": {}, "第1步足：短而粗壮，长节稍长于螯，长约为宽的3倍，腕节短而宽阔，略呈三角形，末缘深深地凹陷，与指节约等长，长约为宽的1．3倍，螯长约为宽的1．8倍，指节约为掌部的1．4倍": {}, "第5步足：约伸至第1触角柄的末端": {}, "掌节：的前后缘均具许多刺，长约为宽的8．5倍，约为指节的3．2倍，指节长约为宽的4．6倍，腹缘具41枚疏状刺": {}, "雄性：第1腹肢内肢外缘凸而内缘凹陷，略呈C形": {}, "内附肢：由内末角伸出，有约一半超出内肢的末缘": {}, "第2腹肢：雄附肢短而粗壮，略呈短棒状，约为内肢长的一半，内缘和末端具长刺": {}, "内附肢：约为雄附肢长的0．8倍": {}, "尾肢：外肢的端叶缝具14枚活动刺": {}}, "生境习性": {"生活：于永康村德门洞中": {}}, "分布范围": {"分布：贵州省-黔南布依族苗族自治州-荔波县": {}}}, "table": {}}