{"summary": {"扭颈绞管螺：（Streptoderatrachelostropha(Moellendorff,1885)）是烟管螺科绞管螺属的一种动物": {}}, "main_body": {"生长环境": {"一般：生活在灌木丛、草丛中,石块、落叶下,树洞、土石缝中,亦栖息于多地衣、苔藓的树干、墙壁、岩石上": {}}, "形态特征": {"形态：贝壳小型，右旋，稍透明，呈纺锤形": {}, "有9个：螺层，各螺层膨胀，最后一螺层分离向下拉长，在前面压扁，基部脊突": {}, "前：几个螺层增长快，螺旋部长，呈圆柱状": {}, "壳：面呈淡黄色，并具有细致的螺纹": {}, "壳顶：钝圆": {}, "缝合线：深": {}, "壳口：呈椭圆梨形，薄，口缘扩大，外折": {}, "上板：边缘高，倾斜，并与螺旋板相连，在下边缘分离，粗壮": {}, "下：襞褶在上，下轴板隐蔽": {}, "在：体螺层右侧壳面上可见到主襞褶、腭褶和月状襞": {}, "主襞褶：短，上腭褶短，下面分离，较深": {}, "月：状褶背面狭小、收缩": {}, "上颚：胼胝呈褶状，在表面较深，与上板对生": {}, "标本测量：壳高10．75mm，壳宽2．5mm，壳口高2．47mm，壳口宽3．18mm。": {}}}, "table": {}}