{"summary": {"拟角库螋：（CosmiculasubcornutaYangetZhang,1992）是球螋科库螋属的一种动物": {}}, "main_body": {"形态特征": {"体表：污黑色，后翅翅柄基部中央有1杏红色斑点，顶端淡红色，触角黑色，第": {}, "8：-9节的端部淡黄色，足的胫节、跗节及尾铗端部有时为红褐色": {}, "头部：较宽，侧后缘圆弧形，额部圆隆，头缝明显": {}, "复眼：较大，几与面颊等长": {}, "触角：细长，圆柱形，基节长大，棒状，具短刚毛，第2节短小，长宽几等，第3节和第4节等长，其余各节逐节稍增长": {}, "前胸：背板约与头部等宽，长宽几等，两侧向后稍收缩，后缘圆弧形，背面前部圆隆，中沟明显，两侧各有l小坑，两侧边稍向上翘，颜色较淡": {}, "前翅和后翅：发达，鞘翅长约为前胸背板长的2倍，肩角明显，侧缘前2／3具脊，后缘接近截形，表面遍布细小刻点": {}, "腹部：两侧弧形，散布横向皱纹，第3-4节的背板两侧各有l个瘤凸": {}, "末腹：背板两侧强度向后变窄，后缘中部横直，表面光滑，从基部向后倾斜，接近基部两侧各有l个角突": {}, "亚末腹：板后缘圆弧形": {}, "臀板：小，背面不可见": {}, "尾铗：弧弯形，两支基部接近而宽，其后的3／4部分较细，圆柱形，顶端尖，相互交叉，顶端前的内缘有1小齿突": {}, "足较：细长，腿节和胫节较细，几呈圆柱形，后足跗节的第l节约为第3节长的1．5倍": {}, "阳茎：叶长大，端部横直，阳茎端刺细长，阳茎基侧突较短小": {}, "雌虫：末腹背板基部两侧无角突，臀板半圆形，从背面可见": {}, "尾铗：细长，向后直伸": {}, "体长": {"8：～12．5mm": {}, "尾铗：长：6-7．5mm(♂)，5mm(♀)": {}}}, "分布范围": {"分布：贵州(梵净山)。": {}}}, "table": {}}