{"summary": {"晶莹蟳：（学名：Charybdislucifera）为梭子蟹科蟳属的动物": {}, "分布：于日本、泰国、马来亚、印度尼西亚、斯里兰卡、印度、台湾岛等地，多生活于海水": {}}, "main_body": {"形态特征": {"头胸甲：上光秃无毛，但有颗粒痕迹": {}, "分区：不明，鳃区各具2斑点，内斑较外斑为大": {}, "表面：的横行隆线，有下列数条，额区具一中断的横行隆线，侧胃区各有一条短的": {}, "中：胃区有一条较长的，最长的一条介于最后侧刺之间，但在踪、胃区之间被颈沟所隔断，在后胃区也中断": {}, "额分6齿：，居中的4枚略等大，但第一侧齿较锐而略向外指，它与第二侧齿有一深缺刻相隔，后者较前者为窄而且较背眼窝绿的内角(呈三角形)为突出": {}, "前侧：绿具6齿，自第一至第五齿逐渐增大，但末齿最小，呈剌状": {}, "雄性：腹部第六节宽大于长，两侧缘几乎平行": {}, "螯足：不甚对称，长节的前缘具3刺，基部的一枚最小，腕节内末角具一壮刺，外侧面具3钝刺，掌节背面具短剌5枚，一枚在腕节之前，2枚接近指节的基部，其他2枚在2条隆脊的中部，大赘的指节较掌节略短": {}, "游泳：足长节的后缘近末端处具一刺，前节的后缘具锯齿约5枚": {}, "头胸甲：长61毫米，宽95毫米": {}}, "生境习性": {"多：生活于海水中": {}}, "地理分布": {"分布：日本、泰国、马来亚、印度尼西亚、斯里兰卡、印度、台湾岛等地": {}}}, "table": {}}