{"summary": {"曲节长柄茧蜂：，Streblocerapanda（Chou，1990），是膜翅目茧蜂科长柄茧蜂属的一种昆虫": {}}, "main_body": {"形态特征": {"雌：体长2.1mm": {}, "触角：2.1mm": {}, "前翅：2.1mm": {}, "产卵管鞘：0.2mm": {}, "体褐：黄色": {}, "胸部：背方暗褐色，腹部褐色": {}, "触角：黄褐色，鞭节褐色": {}, "足：黄褐色": {}, "翅：透明，翅痣和翅脉黄褐色": {}, "产卵管鞘：暗褐色": {}, "头：背面观宽为长的1.4倍(图版ⅩⅦ：137)，为中胸背板宽的1.5倍": {}, "复眼：高为长的1.3倍，为上颊的1.4倍(图版ⅩⅩ：167)": {}, "POL：与OOL之比为0.46": {}, "POL：与OD之比为1.5": {}, "额：光滑，沿复眼具稀毛(图版Ⅻ：107)": {}, "触角：15节": {}, "柄节：长而扩大": {}, "长为：宽的4.8倍和头高1.5倍": {}, "没有：角突": {}, "第：l鞭节强度弯曲，端部腹方有钩状突，第1、2鞭节腹方有1束密毛": {}, "第1鞭节：有9个感觉器": {}, "长为：宽的4.7倍，为柄节的0.4倍，为梗节的2.0倍和第2鞭节的2.0倍，并稍长于第2—3鞭节之长度": {}, "第2鞭节：有5个感觉器": {}, "长为：宽的2.0倍和第3鞭节的1.2倍": {}, "第3鞭节：有5个感觉器": {}, "柄节：长：梗节至第l鞭节长：第2鞭节至端部长=1：0.6：1.6": {}, "颜面：宽为复眼高的1.2倍，为头宽的0.52倍(图版Ⅻ：107)": {}, "颜面和唇基：具柔毛，高为颜面宽的1.0倍": {}, "唇基：下缘有一对小瘤突": {}, "幕骨：陷指数为0.61": {}, "颚眼距：为上颚基宽的1.0倍和复眼高的0.35倍": {}, "后头：脊在背方突出，中央的间断较宽": {}, "胸长：为宽的1.6倍": {}, "中胸：背板光滑，沿盾纵沟仅具稀疏毛": {}, "盾：纵沟具平行刻条(图版ⅩⅩⅥ：227)": {}, "基：节前沟窝状(图版ⅩⅩⅪ：256)": {}, "并胸腹节：基脊和中区发达，中区稍具模糊皱褶(图版ⅩⅩⅪⅤ：286)": {}, "翅：前翅长为宽的2.8倍": {}, "翅：痣长为宽的3.3倍": {}, "1：-R1脉长为翅痣的0.47倍": {}, "r：脉长为翅痣宽的0.38倍": {}, "后足：腿节长为宽的6.3倍": {}, "后足：胫节长为基跗节的2.8倍": {}, "腹：第l背板具中脊": {}, "长为：端宽的1.6倍": {}, "两气门：间距为气门至端部距离的0.9倍(图版ⅩⅩⅩⅥ：315)": {}, "产卵管鞘：长为后足基跗节的0.6倍": {}, "雄：不明": {}}, "国内分布": {"分布：台湾（雾社）": {}}}, "table": {}}