{"summary": {"梳齿毛根蚜：（ChaetogeoicafolidentataTao,1947）是瘿绵蚜科毛根蚜属的一种动物": {}}, "main_body": {"形态特征": {"无翅干母新型记述": {"体：椭圆形，长1．31，宽0．68mm": {}, "活体：黄色，分泌长蜡丝": {}, "玻片标本：头与前胸黑褐色，腹部淡色，无斑纹": {}, "触角、喙、复眼、足：各节、尾片及尾板黑褐色": {}, "体表：光滑": {}, "腹部：背片Ⅷ有1对孔状突起": {}, "体背：蜡片淡色，由8—35个不规则蜡胞组成": {}, "头部：缺蜡片": {}, "前胸：背后缘中域1对小蜡片，由3或4个小蜡胞组成，缘蜡片大型，中、后胸各1对大型中蜡片，缘蜡片1对": {}, "腹部：背片Ⅰ—Ⅶ各中、缘蜡片各1对，侧蜡片偶有，Ⅷ一连续横带状蜡片": {}, "尾片及尾板：均密布蜡胞": {}, "气门：关闭，气门片黑色": {}, "中：胸腹岔两臂分离，臂长0．067mm，与触角节Ⅱ约等": {}, "体背毛：短尖锐，头顶毛2对，头背毛6对": {}, "前胸：中毛2对，缘毛3对": {}, "背片Ⅰ—Ⅶ缘毛：各2对，中毛3或4根，侧毛1—2对，Ⅷ共1对极短毛": {}, "头顶及背片Ⅰ毛长0．：013—0．014mm，为触角节Ⅲ最宽直径0．52—0．56，Ⅷ毛长0．004mm": {}, "头：平顶，淡色头盖缝明显": {}, "复眼：突出由3小眼面组成": {}, "触角5节：，有皱褶纹，全长0．37mm，为体长0．28，节Ⅲ长0．095mm，Ⅰ—Ⅴ长度比例：44，73，100，60，80+36": {}, "Ⅰ：—Ⅴ毛数：3或4，5或6，2—4，2或3，1或2+4根，Ⅲ毛长0．006mm，为该节最宽直径0．24": {}, "喙：短，不达中足基节，节Ⅳ+Ⅴ楔状，长0．06mm，为基宽1．40倍，为后跗节Ⅱ0．53，有短毛3对，其中次生毛1对": {}, "足：各节有微瓦纹，后股节长0．24mm，与触角节Ⅲ—Ⅴ之和约等": {}, "后：胫节0．29mm，为体长0．22，毛长0．012mm，为该节最宽直径0．380跗节Ⅰ毛序：3，3，3": {}, "无：腹管": {}, "尾片：末端圆形，有1对短刚毛": {}, "尾板：末端平圆，有毛21或22根": {}, "生殖：板黑色，有长毛18—21根": {}}, "无翅孤雌蚜新型记述": {"体：椭圆形，长1．13，宽0．69mm": {}, "头部：淡色，背中域及头顶部褐色，胸、腹部淡色，无斑纹": {}, "蜡片：明显，由小圆形蜡胞组成，头部背中蜡片2对": {}, "前胸：背后缘1对大形蜡片，由20—30个蜡胞组成，缘蜡片1对，中、后胸及腹部背片Ⅰ—Ⅶ各有中、侧、缘蜡片1对，蜡片均由25—50个蜡胞组成，Ⅷ1对中蜡片，足各基节各蜡片1对": {}, "触角6节：，全长0．408mm，节Ⅲ长0．073mm，Ⅰ—Ⅵ长度比例：58，75，100，66，89，118+53": {}, "其他：特征与无翅干母相似": {}}, "有翅孤雌蚜": {"体：椭圆形，长1．613，宽0．684mm": {}, "活体：淡黄色": {}, "玻片标本：头、胸部黑褐色，腹部淡色，无斑纹，触角、喙、足、尾片、尾板及生殖板黑褐色": {}, "体表：光滑，腹部背片Ⅵ、Ⅶ及Ⅷ有瓦纹": {}, "体背：有暗色周围无界线的蜡胞群": {}, "前胸：背中及缘蜡孔群各1对": {}, "腹部：背片Ⅰ—Ⅶ有中蜡胞群，各由15—30余个蜡孔构成，Ⅰ—Ⅶ各缘蜡孔群独立，各由15—20余蜡胞构成，与陶，1970记述，仅有缘蜡片7对，每片有3—7个蜡胞，明显有不同": {}, "头：背有时有暗色分散蜡胞群，Ⅷ缺": {}, "气门：圆形开放，气门片淡褐色": {}, "体背毛：尖锐，头顶毛2对，头背毛7—8对": {}, "腹部：背片Ⅰ—Ⅵ各中侧毛5—8对，Ⅶ中侧毛3对，Ⅱ—Ⅶ缘毛各4—5对，Ⅰ缘毛3对，Ⅷ毛共5或6根": {}, "头顶：毛长0．013—0．024mm，为触角节Ⅲ最宽直径0．32—0.60，头背毛极短为毛孔的1．50倍，背片Ⅰ缘毛长0．011，Ⅶ毛长0．025，Ⅷ毛长0．030mm": {}, "中额：平圆，中央凹入，有明显头盖缝，延伸至后缘": {}, "触角6节：，全长0．460mm，为体长0．29，有粗横瓦纹": {}, "节Ⅲ长0．：101mm，Ⅰ—Ⅵ长度比例：41，42，100，78，78，80+39": {}, "次生：感觉圈大圆至横椭圆形，有睫，节Ⅲ7或8个，Ⅳ4或5个，各分布全长，Ⅴ0或1个，靠近原生感觉圈": {}, "毛：尖锐，Ⅰ—Ⅵ毛数：4，4或5，1—4，4—6，4或5，4或5+4或5根，节Ⅲ毛极短，为该节最宽直径1／3—1／6，余节毛较长": {}, "喙：不达中足基节，Ⅳ+Ⅴ宽楔状，近端部收缩，长0．093mm，为基宽1．80倍，为后跗节Ⅱ0．90，有短毛4—5对，其中次生毛2—3对": {}, "足：股节有微瓦纹，后股节长0．296mm，为触角节Ⅰ—Ⅳ之和的1．10倍": {}, "后：胫节长0．483mm，为体长的0．30，毛长为该节最宽直径0．60": {}, "跗节Ⅰ毛序：": {}, "3：，3，3": {}, "翅脉：淡色，前翅中脉不分支，两肘脉基部相合无柄(与陶，1970记述肘脉1在基部1／3处与肘脉2共柄显有不同": {}, "后翅：两肘脉非平形，基部有一共柄，中间有一段不显(与陶，1970记述也不同)": {}, "无：腹管": {}, "尾片：小半球形，有微瓦纹，长0．035mm，为该基宽0．38，有短毛6或7根": {}, "尾板：末端圆，毛17—22根": {}, "生殖：板毛27—30根，位于后部": {}, "生殖：突1对，有粗尖毛16—18根": {}}}, "分布范围": {"分布：山东(泰安),江苏(南京),浙江,四川,云南(大理)": {}}}, "table": {}}