{"summary": {"森毛苔螋：（ChaetospaniasilvestriiBorelli,1927）是苔螋科毛苔螋属的一种动物": {}}, "main_body": {"形态特征": {"体型：甚狭小而扁平，暗褐色，触角浅褐色或暗褐色，口部、触须和足通常黄色，腹部和尾铗褐红色，但深浅不一": {}, "头部：扁宽，面颊圆弧形，后缘弧凹形，额部中央有1凹形三角区，中缝明显": {}, "复眼：小而突出": {}, "触角：细长，9-13节，基节长大，棒状，第2节长宽几等，第3节细长，第4节稍长于第2节，第5节长于第4节，其余各节较细长": {}, "前胸：背板长稍大于宽，两侧平行，后缘弧形，背面前部稍圆隆，中沟明显，两侧各有l小隆凸，后部平，具明显刻点": {}, "鞘翅：相对较短，短于前胸背板长的2倍，两侧平行，后缘几横直，表面密布小刻点和灰白色绒毛": {}, "后翅：发达，翅柄长约为前翅长的l／2，外缘斜弧形，表面密布小刻点": {}, "腹部：狭长，遍布刻点和灰白色绒毛，两侧弧形，第3-4节背面两侧的隆凸明显": {}, "末腹：背板短宽，两侧平行，后缘接近横直，后部背面两侧各有l隆凸，雌虫后部收缩": {}, "亚末腹：板短宽，两后外侧弧形，后缘稍呈弧凹形，表面散布小刻点和绒毛": {}, "雌虫：的后端收缩": {}, "臀板：长大，具4个角突，侧缘中央l个较小，后缘侧角尖长，后缘中凹甚深，背面光滑，微凹": {}, "雌虫：臀板简单，长大于宽，接近长方形": {}, "尾铗：向后直伸，顶端尖，向内侧弯曲，内缘底部齿突之前扩展，雄虫的齿突位于中后部，雌虫的齿突在前部，遍布较短黄绒毛": {}, "足：短粗，黄色或褐黄色，被黄色绒毛，腿节甚短粗，接近椭圆形，后足第1跗节较长": {}, "体长": {"6：．2-7．3mm": {}, "尾铗：长：1．8-2．2mm": {}}}, "分布范围": {"国外分布：越南，不丹，缅甸。": {}, "国内分布：广西（那坡弄化），云南，西藏（墨脱甘代）。": {}}}, "table": {}}