{"summary": {"毛肘虞索金小蜂：（SkelocerasnovickyiDelucchi,1953）是金小蜂科虞索金小蜂属昆虫": {}}, "main_body": {"形态特征": {"雌：：体长4mm": {}, "体亮：蓝绿色": {}, "触角：柄节、梗节蓝绿色，鞭节黑褐色": {}, "足：基节、腿节亮蓝绿色，胫节、跗节暗褐黄色至浅棕色": {}, "翅：透明": {}, "前：翅基脉后部一半褐黄色，其余翅脉浅棕色": {}, "头：前面观宽为高的1．3倍": {}, "触角：窝中单眼距略大于触角窝唇基下端距(18：15)": {}, "下脸：中央略膨起": {}, "口上：沟清晰": {}, "唇基：表面具细小刻点，下端3齿不对称，左、中齿合起来形如右齿": {}, "头：侧面观高为长的1．9倍": {}, "颚眼：沟清晰": {}, "颚眼距：为眼高的1／3": {}, "头：背面观宽为长的2．3倍": {}, "上颊：长为眼长的1／3": {}, "POL：等于OOL": {}, "触角：柄节长为眼高的0．6倍，上端不达中单眼": {}, "梗节：加鞭节为头宽的1．5倍": {}, "梗节：略长于宽": {}, "基部4索节：等长，长约为宽的1．8～2倍，端部3索节逐节缩短，第七索节长为宽的1．6倍": {}, "棒节：长为宽的3倍，第七索节和第一棒节等长": {}, "感觉：毛不明显，各索节和棒节约具3排": {}, "触角：毛短而密": {}, "中胸：盾片宽为长的1．4倍，其长略大于小盾片(32：30)": {}, "小盾片：横沟深而完整": {}, "沟：前域中央纵凹沟仅前部明显": {}, "沟：后片两侧纵脊明显，中部具刻点": {}, "小背板：具刻点": {}, "中脊：锋锐、完整，侧褶后部锋锐，中脊中部有一横脊和侧褶相连或横脊在近中脊处弱，在横脊的前后有不规则的斜脊": {}, "前：翅基室端部具毛，后缘关闭": {}, "肘脉：完整": {}, "基脉：外透明斑大，后缘关闭": {}, "后缘：脉长为缘脉的1．4倍，缘脉长为痣脉的1．4倍": {}, "痣：矩形，宽为长的2倍，痣钩长等于痣宽": {}, "后翅：前缘室光裸": {}, "腹柄：宽为长的1．25倍，前缘横脊粗壮，两侧略向外突起": {}, "柄：后腹长为宽的2倍": {}, "柄：后腹第一节背板占柄后腹全长的1／3": {}, "雄：：未知": {}, "检视标本：西藏芒康，3250m，1982．Ⅷ．12，1♀，王书永采。": {}}, "分布范围": {"国内分布：西藏": {}, "国外分布：英国,瑞士": {}}, "参考文献": {}}, "table": {}}