{"summary": {"菩拟乔球螋：（ParatimomenusbrahmaBurr,1904）是球螋科拟乔球螋属的一种动物": {}}, "main_body": {"形态特征": {"体型：细长，浅黑褐色，头部、前胸背板两侧和足灰黄色或黄色": {}, "头部：两侧向后稍收缩，后缘弧凹形，额部圆隆，光滑，头缝不明显": {}, "复眼：突出，灰白色": {}, "触角：细长，12节，10～11节灰白色，基节长大，棍棒形，第2节细小，长稍短于宽，第3节稍细长，第4": {}, "节：稍短于第3节，但较粗，第5节长于第3节，其余各节较细长": {}, "前胸：背板接近方形，后缘弧形，背面前部圆隆，除侧边外呈暗褐色，后部平，散布明显刻点": {}, "鞘翅：狭长，肩角圆弧形，两侧平行，后缘稍向后内侧倾斜，表面平滑": {}, "后翅：翅柄发达，外缘弧形，顶端有1浅黄色小斑": {}, "腹部：狭长，两侧向后稍扩展，遍布较密刻点和皱纹，第3～4节背面两侧各有1瘤凸": {}, "末腹：背板稍短宽，两侧向后收缩，后缘中央弧凹形，背面拱形，光滑，接近后缘两侧各有1瘤凸": {}, "亚末腹：板后缘圆弧形，表面散布小刻点和皱纹": {}, "臀板：后缘圆弧形，中央具压迹": {}, "尾铗：细长，中部有1较大齿突，其前的内缘稍呈直弧形，其后弯度较大，顶端细而尖": {}, "足：长大，腿节发达": {}, "雄性：阳茎基侧突外缘弧形，顶端稍尖，阳茎端刺细长，波弯形": {}, "体长": {"10：～12mm": {}, "尾铗：长：4．5-6mm": {}}}, "分布范围": {"国外分布：越南，不丹，印度北部。": {}}}, "table": {}}