{"summary": {"蒙自米虾：（CaridinamongziensisLiang，YanetWang,1987）是匙指虾科，米虾属的一种动物": {}, "额角：较短，基部稍隆起，末端略向下低，通常伸至靠近第1触角柄第2节的末端或稍微超出": {}, "上缘：具9—11齿，分布于额角的基半部，基部有5—7(通常为6)齿位于眼眶后缘的头胸甲上，额角末端约1/2－2/3无齿": {}, "下缘：具1—4(通常为3)齿，分布于上缘末齿的前方，紧靠额角的末端": {}, "头胸甲：的前侧角圆，无颊刺": {}}, "main_body": {"形态特征": {"尾节：背面具5—6对背刺，后端中央背面具一尖突": {}, "侧：刺短，仅为外后刺的2倍": {}, "间：刺3—4对，与侧刺约等大": {}, "肛前脊：顶端圆钝，末端生许多刚毛": {}, "第1触角：柄刺长，约伸到基节的末端，第1节约为第2节的1．6倍，第2节与第3节约等长": {}, "第2触角：鳞片长约为宽的2．9—3．0倍": {}, "第1颚足：内肢的外末角具一指状突起": {}, "第3颚足：约伸至鳞片的末端": {}, "末节：稍短于末2节而长于末3节，在末3节的外侧列生有规则的短簇毛，末节末端爪状，末端腹侧具7枚短刺": {}, "第1步足：短而粗，约伸至第1触角柄第2节的末端": {}, "座：节约为长节的1/2．5，长节与腕节近等长，腕节稍短于螯，末端深凹，长为宽的1．8—2．3倍，指节为掌长的1．1—1．2倍，螯长为宽的2．2—2．4倍": {}, "第2步足：较细长，约伸至第1触角柄第2节的末端": {}, "座：节约为长节的1/2．3，长节稍短于腕节，腕节长于螯，末端稍凹陷，长为宽的4．4—4．9倍，指节为掌长的1．2—1．4倍，螯长为宽的2．7—3．0倍": {}, "第3步：足掌节约1/4超出鳞片的末端": {}, "座：节约为长节近1/3，长节约为腕节的1．4倍，腹缘约具3刺，腕节约为掌节的0．8倍，末腹缘与末腹角均具刺，掌节长约为末端宽的7．9倍": {}, "为：指节的3．2—3．4倍，指节长为宽的3．4—3．5倍，腹缘通常具6个活动刺": {}, "第5步足：指节约伸至第1触角柄第2节的末端": {}, "座：节约为长节的1/3．5，长节约为腕节的1．3倍，腹缘具3刺，腕节约为掌节的0．6倍，腹缘与末腹角均具刺，掌节长约为末端宽的9．8倍，为指节的4．0—4．1倍，指节长为宽的3．4—3．6倍，腹缘具35—40个疏状刺": {}, "雄性：第1腹肢内肢略呈长方形，基部稍宽于末部，内缘中部凹陷，基部2/3排列有许多短刺，外缘几平直，仅在基部约1/3处稍稍的向内凹，基半部具羽状刚毛，细而长，末半部和末端为粗刺，刺明显的较刚毛为稀疏，且由基部向末端逐渐变粗变长，末端亦为粗短刺，由内向外侧逐渐变长变粗": {}, "内附肢：由内侧近中部伸出，短而粗，伸至超出内肢的末端，末端列生有数个小钩": {}, "第2腹肢：雄附肢呈棍棒状，刺较短而数多，由基部一直分布到整个内侧的末端，在基部和末端的刺较短小，在中部和内末缘则较粗长": {}, "内附肢：粗壮，其长度不超过雄附肢的1/2，末端密布小钩": {}, "尾肢：外肢的端叶缝具13—18个活动刺": {}, "体长：为21—36mm": {}, "卵径：为0．93mm—1．07mm×1．35mm—1．59mm": {}}, "生境习性": {"生活：于水质清澈的水库入水的溪流中": {}}, "地理分布": {}}, "table": {}}