{"summary": {"薄宽口梭螺：（Aperiovulashikamai）是梭螺科，宽口梭螺属的一种动物": {}}, "main_body": {"形态特征": {"贝壳：呈长卵圆形或梨形": {}, "壳质：较厚，后部较宽，向前逐渐变瘦，壳面白色或淡肉色，表面粗糙，有波折的螺旋纹和纵行生长纹": {}, "壳口：窄长，前部较宽敞": {}, "索带：发达，其上有齿状突起": {}, "外唇：宽厚，具齿列，延伸至外唇边缘形成小颗粒状突起": {}, "贝壳：为长卵圆形，壳质较薄，前端较尖瘦，后端凸出": {}, "壳面：不光滑，具有纵走而明显的生长线，有时形成皱褶": {}, "并：满布宽窄不一、近似波状横的沟纹，这些沟纹并向基部延伸": {}, "基部：的中部稍隆起，壳口较宽，内唇近后端的脐带小，近三角形，光滑": {}, "在内：唇外缘前部约1/3处具一形似龙骨状突起": {}, "壳：轴的龙骨明显，前渠浅": {}, "外唇：薄，边缘稍向内卷(上部边缘有破损)，内缘不见有突起状的齿(可能是壳较年轻)": {}, "壳：表面灰白色，其前端隐约可见桔黄色的线纹": {}}, "生活习性": {"生活：在潮下带，栖水较深，我们曾在水深90m、褐色泥沙质的海底，采到一个较年较的生活标本": {}, "据：Azuma(1976)报道，水深50--100m的海底也有栖息，寄主不详": {}}, "分布范围": {"分布：除在东海我国浙江温州以东外海及日本的土佐湾分布外，其他海区尚无报道，故为中国和日本特有种。": {}}, "主要价值": {"可食用：": {}}}, "table": {}}