{"summary": {"蛞蝓指环虫：（DactylogyruslimaciformisTaoetLong,1981）是指环虫属昆虫": {}}, "main_body": {"形态特征": {"成虫：形态小型蠕虫，体长0.25-0.28mm，宽0.065-0.081mm，咽0.015-0.020×0.015-0.016mm": {}, "边缘：小钩长0.012-0.021mm，第4对最长，第7对最短": {}, "柄、柄：轴和钩尖基突明显": {}, "中央大钩：全长0.032-0.038mm，基部长0.022-0.023mm，钩尖长0.008mm，内突0.014-0.016mm，外突0.0008-0.0015mm": {}, "联结：片直形，两端稍膨大，0.0015-0.0023×0.014-0.018mm": {}, "交接管：细长，全长据弯度0.019-0.025mm，基径0.005mm，中部管径0.0008mm": {}, "支持器：基部由二几丁质棒与交接管管基相接，中部由一翼状骨片与数根小棒构成一支架，其上均覆以薄膜而构成一罩子，交接管均在罩内，最后于罩顶伸出一烟囱状膜状结构，交接管即由此通出，整个交接器粗看似一只蛞蝓": {}, "阴道与卵：未见": {}, "图：310蛞蝓指环虫Dactylogyuslimaciformis": {}, "1：．后吸器": {}, "2：．交接器": {}, "（：仿自陶水生、郎所）": {}, "（：姜乃澄）": {}}, "生活习性": {"宿主：:泸溪直口鲮": {}, "寄生部位：:鳃丝": {}}, "分布范围": {"分布：贵州": {}}, "参考文献": {}}, "table": {}}