{"summary": {"裂细粉蚧：（CannococcusostiolataBorchsenius,1958），属于动物界、同翅目、粉蚧科": {}}, "main_body": {"形态特征": {"雌成虫": {"体：椭圆形": {}, "体长：约4mm": {}, "触角和足同：虫体相比均显得很细小": {}, "触角6节：，其中第2节、第3节和顶端节较长": {}, "喙：小，分为2节": {}, "胸气：门边有多孔腺宽带一直延伸至体缘": {}, "在：气门附近多孔腺的分布比体缘的多孔腺带更为浓密": {}, "后足：基节具大透明孔": {}, "前背裂：缺": {}, "后背：裂虽小，但明显存在": {}, "腹裂：常为4个，有时具5个，最上方的腹裂有时缺所以是4个": {}, "如果：最上方的腹裂存在时，虽呈5个腹裂，但最上方的腹裂比其余的均小，而最下方一个则是最大者": {}, "肛环：宽，几乎为圆形，具很多圆形孔和6根肛环刺": {}, "臀瓣：不发达，在臀瓣刺附近还生有2—3根毛": {}, "臀瓣：背面具刺孔群": {}, "刺孔群：只一对，该刺孔群由2根粗的圆锥形刺组成": {}, "多孔腺：沿体缘形成宽带，在虫体背面也常集成群分布，在腹部第6和第7节腹板上形成横带": {}, "管状腺：在体缘加入多孔腺带里杂乱分布": {}, "管状腺：的分布数量越向虫体后端越多": {}, "在：虫体腹面两侧还能见到零星分布的管状腺": {}, "体毛：数量很少而短，只是在腹部第7和第8节上有较长的体毛，但也是较稀疏的分布": {}}}, "生活习性": {"寄主：:芦苇": {}}, "分布范围": {"分布：浙江": {}}, "参考文献": {}}, "table": {}}