{"summary": {"角库螋：（CosmiculacornutaBey-Bienko,1959）是球螋科库螋属的一种动物": {}}, "main_body": {"形态特征": {"体型：狭长，暗褐色或红褐色，头部浅红褐色，足浅褐红色": {}, "头部：短宽，后角稍圆，后缘稍呈弧凹形": {}, "复眼：大而突出，与面颊几等长，额部圆隆，头缝明显": {}, "触角：11节，端节颜色较浅，基节长大，棒状，第2节短小，第3节较细，第4节稍长于第3节，第5节长于第4节，其余各节较细长": {}, "前胸：背板接近方形，后缘弧形，侧边灰黄色，背面前部圆隆，中沟明显": {}, "鞘翅：短缩，外缘长于内缘，后缘向内缘斜截，表面平": {}, "后翅：不发育": {}, "腹部：两侧弧形，第3-4节的背面两侧各有l个瘤凸，遍布细密刻点和皱纹": {}, "末腹：背板两侧向后强度收缩，接近三角形，背面光滑，基部两侧各有1个尖角突，后缘稍呈弧形": {}, "亚末腹：板后缘弧形，表面散布刻点和皱纹": {}, "臀板：小，背面不可见": {}, "尾铗：长大，基部较粗，两支接近，其后向外强度弯为弧形，圆柱形，顶端尖，相互交叉，稍前变粗，有1不明显小齿突": {}, "足：细长，腿节和胫节较细而圆，后足跗节的长约为第3节长的1．5倍": {}, "雌虫：末腹背板两侧无刺突，尾铗细长，不弯曲，顶端细而尖，向内侧弯": {}, "体长": {"9：．5～12mm": {}, "尾铗：长：5．5-9mm": {}}}, "分布范围": {"分布：云南(无量山)。": {}}}, "table": {}}