{"summary": {"赤杨刻斑蚜：（ClethrobiusdryobiusChakrabartietRaychaudhuri,1976）是斑蚜科刻斑蚜属的一种动物": {}}, "main_body": {"形态特征": {"有：翅孤雌蚜体长椭圆形，体长3．98mm，体宽1．41mm": {}, "玻片标本：头部和胸部、触角、足及喙褐色": {}, "腹部：淡色，各足股节基部淡色，触角节Ⅲ黑褐色": {}, "腹部背板：缘斑明显着色": {}, "背片Ⅷ全节：褐色横带": {}, "尾片和尾板：褐色，腹管褐色": {}, "触角：节Ⅳ端部、节Ⅴ—Ⅵ、跗节Ⅱ横瓦纹": {}, "尾片及尾板：小刺突": {}, "体背毛：尖锐，数量多，长短相近": {}, "头顶：毛2对，头背触角节Ⅰ间毛3对，复眼间毛6对": {}, "前胸：背板密被长毛": {}, "腹部：背片Ⅰ—Ⅶ缘毛各28—34根，中侧背毛14—20根": {}, "背片Ⅷ有：毛29根": {}, "头顶：毛长0．11mm，腹部背片Ⅰ缘毛长0．13mm，背片Ⅷ背毛长0．16mm，分别为触角节Ⅲ最宽直径1．57倍、1．71倍及2．14倍": {}, "中胸：背板蜡片存在": {}, "中额：平直，额瘤不显": {}, "触角6节：，全长2．99mm，节Ⅰ—Ⅵ长度比例：7：4：100：43：34：12＋10": {}, "触角：末节鞭部为基部0．83倍": {}, "触角：毛似体背毛，节Ⅰ—Ⅵ毛数：20、9、110、34、26、3＋0，末节顶端有毛4根": {}, "节Ⅲ有：长卵形具睫次生感觉圈57—62个，分布在近基部7／10": {}, "喙：端刚达中胸腹板前缘": {}, "喙：节Ⅳ＋Ⅴ较粗短，长0．16mm，为基宽1．55倍，与后足跗节Ⅱ等长": {}, "端部：有毛12对，其中次生毛9对": {}, "足：各节正常": {}, "后足：股节长1．41mm，为触角节Ⅲ1．02倍": {}, "后足：胫节端部内侧有一列钉状毛": {}, "长2．：54mm，为体长0．64倍": {}, "跗节Ⅰ毛序：：7，7，7": {}, "腹管：短柱状，长0．10mm，为基宽0．75倍，为尾片1．11倍": {}, "周围：有1—4根毛环绕": {}, "尾片：基部收缩，中部稍收缩，长0．09mm，与基宽约等": {}, "端部：有毛20余根": {}, "尾板：完整，有毛40余根": {}, "生殖：突有一丛毛28根": {}, "有：翅若蚜体长椭圆形，体长3．50mm，体宽1．68mm": {}, "玻片标本：触角、喙、足各节、腹管、尾片、尾板及翅芽为褐色，其余淡色": {}, "体背毛：粗长尖，有毛基斑": {}, "体：腹面毛较背毛短而细": {}, "腹部：背片Ⅷ背毛毛基斑较大": {}, "气门：卵圆形，气门片圆形至卵圆形，褐色": {}, "触角：节Ⅲ次生感觉圈缺": {}, "胚胎：背毛尖，长": {}, "缘毛3对：": {}, "侧毛：存在": {}, "中：背毛4根": {}, "观察：标本1头有翅孤雌蚜和1头有翅若蚜，贵州(清正)，1980-Ⅸ-10，No．Y1993，寄主：化稿，刘井文采": {}}, "分布范围": {"国内分布：贵州": {}, "国外分布：印度": {}}}, "table": {}}