{"summary": {"长粉蚧：（TangicoccuselongatusTang,1977）是粉蚧科长粉蚧属的一种动物": {}}, "main_body": {"形态特征": {"雌成虫": {"体：细长，扁平，虫体两侧边几乎平行": {}, "体：最长约10.26mm，最宽约3.14mm，通常其体长约为其宽的三倍以上": {}, "老熟：之虫体多硬化，呈黄褐色，腹部末端数节则强烈硬化": {}, "虫：体外无蜡被所覆盖": {}, "口器：位于胸部中部，在前和后胸气门之间": {}, "喙1节：": {}, "前和后胸：气门较发达，位于体缘一椭圆形之硬化片上": {}, "气门：开口附近有一群三孔腺包围成半月形": {}, "触角：位于头顶体缘之两侧，退化为2节之小瘤状突起，触角之第1节狭环状，第2节长柱形，在第2节顶端生有7—8根细刚毛": {}, "胸足：退化，已完全消失": {}, "前背裂：无": {}, "后背：裂虽存在，但很不明显": {}, "腹裂：无": {}, "肛环：退化，无肛环孔，肛环刺毛只有2根": {}, "腹：末呈叶片状，无臀瓣，每侧常生有3根硬刺毛": {}, "管状腺：只一种类型，呈柱状，其开口处有硬化框围绕，内端略突": {}, "从：后胸气门以后至第6腹节，此管状腺沿着体缘排列成宽带形": {}, "盘：状腺有几乎同形、同大之三孔腺和多孔腺2种": {}, "三孔腺：分布于体缘及腹部背面，多孔腺分布于腹末4腹节之腹面": {}, "细：刚毛见于腹部腹面，在阴门后有成横带排列之一群刺毛": {}}, "第一：龄若虫长椭圆形，胸足与触角均发达": {}, "触角6节：": {}, "肛环：发达": {}, "肛环：具孔和6根肛环刺": {}, "臀瓣：（尾瓣）发达，生有一长端毛": {}, "腹裂：一个": {}, "前背裂：无，后背裂存在": {}, "三孔腺：分布于虫体背和腹两面": {}}, "生长环境": {"寄主：:刺竹属,箬竹属": {}, "常：在竹之叶鞘下寄生": {}}, "分布范围": {"国内分布：浙江,福建": {}}}, "table": {}}