{
  "summary": {
    "东方伪卷叶绵蚜岷亚种：(ThecabiusorientalisminensisZhang,1995)是瘿绵蚜科伪卷叶绵蚜属的一种动物": {}
  },
  "main_body": {
    "形态特征": {
      "无翅孤雌蚜": {
        "体：卵圆形，长2．73，宽1．55mm": {},
        "活体：淡黄或乳白色，分泌长蜡丝": {},
        "玻片标本：头部黑褐色，胸、腹部淡色，无斑纹": {},
        "触角、喙、足各节、尾片、尾板及生殖板：黑褐色": {},
        "复眼：大形，黑色，由三小眼面组成": {},
        "体表：光滑，背片Ⅷ微瓦纹，蜡片淡色，大形，头部有不规则蜡孔组成的蜡片": {},
        "头顶：1对，头部背面5对，由10—15个蜡胞组成，头背表皮满布皱纹，头部腹面满布蜡孔": {},
        "前胸：背中蜡片2对，缘域2对，各由大蜡胞组成": {},
        "腹部：背片Ⅲ—Ⅶ各有大型中侧蜡片各1对，各由200—300个小圆形蜡胞组成": {},
        "气门：圆形开放，气门片黑色": {},
        "节间：斑": {},
        "中胸：腹岔淡色，不甚明显，无柄，有时分离，全横长0．47mm，为触角节Ⅲ1．10倍或等长": {},
        "体背：毛少，尖锐，腹部腹面多毛，短于背毛": {},
        "头顶：有毛2对，头背毛5对，腹部背片Ⅰ—Ⅵ各中侧毛4—7对，Ⅶ2—3对，各节缘毛1对，有时2对，Ⅷ毛2对，有时1对": {},
        "头顶：毛长0．019mm，为触角节Ⅲ直径0．40，背片Ⅰ毛长0．012，Ⅷ毛长0．039mm": {},
        "额：平顶状，微显头盖缝": {},
        "触角：节Ⅲ—Ⅵ由小刺突组成瓦纹，全长1．49mm，为体长0.55，节Ⅲ长0．44mm，Ⅰ—Ⅵ长度比例：24，47，100，45，55，57+10": {},
        "原生：感觉圈有睫": {},
        "节：Ⅰ—Ⅵ毛数：5—8，13—18，15—20，5—7，5—7，2—4+5根，节Ⅲ毛长0．020mm，为该节最宽直径0．41": {},
        "喙：达后足基节，节Ⅳ+Ⅴ楔状，长0．13mm，为该节基宽1．90倍，为后跗节Ⅱ0．44，有毛6对，其中次生毛3对": {},
        "足：光滑，各节少毛": {},
        "后股：节长0．75mm，为触角节Ⅲ—Ⅵ之和的1．20倍": {},
        "后：胫节长1．06mm，为体长0．39": {},
        "后跗节Ⅱ：长0．30mm": {},
        "跗节：Ⅰ各有粗毛4—7根": {},
        "腹管：无": {},
        "尾片：末端圆，端部黑色网纹部分呈月牙状，有毛1对": {},
        "尾板：有毛18—25根": {},
        "板：椭圆形，有长尖锐毛18—22根": {},
        "突毛：有三丛，各有毛4—8根": {}
      },
      "ThecabiusorientalisMordvilko：与之极相似，但腹部背片Ⅶ有蜡片4个(orientalis，2)": {}
    },
    "分布范围": {
      "国内分布：": {},
      "分布": {
        "国内分布：甘肃(岷县2300m，1986-Ⅶ-20，No．8492，张广学、钟铁森；1986：-Ⅶ-11，No．8465，张广学、李静华)": {}
      }
    }
  }
}